Lab 5/MUX8_dataflow.v
module mux8x1 (output Y, input I0, I1, I2, I3, I4, I5, I6, I7, S2, S1, S0);
    wire w0, w1, w2, w3, w4, w5, w6, w7;
    assign w0 = (~S2 & ~S1 & ~S0 & I0);
    assign w1 = (~S2 & ~S1 & S0 & I1);
    assign w2 = (~S2 & S1 & ~S0 & I2);
    assign w3 = (~S2 & S1 & S0 & I3);
    assign w4 = (S2 & ~S1 & ~S0 & I4);
    assign w5 = (S2 & ~S1 & S0 & I5);
    assign w6 = (S2 & S1 & ~S0 & I6);
    assign w7 = (S2 & S1 & S0 & I7);

    assign Y = (w0 | w1 | w2 | w3 | w4 | w5 | w6 | w7);
endmodule

Lab 5/MUX8_tb.v
`include "MUX8_dataflow.v"
module mux8x1_tb;
    reg I0, I1, I2, I3, I4, I5, I6, I7, S2, S1, S0;
    wire Y;

    mux8x1 Instance0(Y, I0, I1, I2, I3, I4, I5, I6, I7, S2, S1, S0);
     initial begin
          S2=0;S1=0;S0=0;I0=1;I1=0;I2=0;I3=0;I4=0;I5=0;I6=0;I7=0;
       #1 S2=0;S1=0;S0=1;I0=0;I1=1;I2=0;I3=0;I4=0;I5=0;I6=0;I7=0;
       #1 S2=0;S1=1;S0=0;I0=0;I1=0;I2=1;I3=0;I4=0;I5=0;I6=0;I7=0;
       #1 S2=0;S1=1;S0=1;I0=0;I1=0;I2=0;I3=1;I4=0;I5=0;I6=0;I7=0;
       #1 S2=1;S1=0;S0=0;I0=0;I1=0;I2=0;I3=0;I4=1;I5=0;I6=0;I7=0;  
       #1 S2=1;S1=0;S0=1;I0=0;I1=0;I2=0;I3=0;I4=0;I5=1;I6=0;I7=0;
       #1 S2=1;S1=1;S0=0;I0=0;I1=0;I2=0;I3=0;I4=0;I5=0;I6=1;I7=0;
       #1 S2=1;S1=1;S0=1;I0=0;I1=0;I2=0;I3=0;I4=0;I5=0;I6=0;I7=1;
       #1 ;
     end

    initial begin
        $monitor("%t | S2=%b | S1=%b | S0=%b | I0=%b | I1=%b | I2=%b | I3=%b | I4=%b | I5=%b | I6=%b | I7=%b | Y=%b",$time,S2,S1,S0,I0,I1,I2,I3,I4,I5,I6,I7,Y);
        $dumpfile("mux_dump.vcd");
        $dumpvars();	
    end
endmodule

Lab 5/mux_dump.vcd
$date
	Tue Oct 11 14:48:42 2022
$end
$version
	Icarus Verilog
$end
$timescale
	1s
$end
$scope module mux8x1_tb $end
$var wire 1 ! Y $end
$var reg 1 " I0 $end
$var reg 1 # I1 $end
$var reg 1 $ I2 $end
$var reg 1 % I3 $end
$var reg 1 & I4 $end
$var reg 1 ' I5 $end
$var reg 1 ( I6 $end
$var reg 1 ) I7 $end
$var reg 1 * S0 $end
$var reg 1 + S1 $end
$var reg 1 , S2 $end
$scope module Instance0 $end
$var wire 1 " I0 $end
$var wire 1 # I1 $end
$var wire 1 $ I2 $end
$var wire 1 % I3 $end
$var wire 1 & I4 $end
$var wire 1 ' I5 $end
$var wire 1 ( I6 $end
$var wire 1 ) I7 $end
$var wire 1 * S0 $end
$var wire 1 + S1 $end
$var wire 1 , S2 $end
$var wire 1 ! Y $end
$var wire 1 - w0 $end
$var wire 1 . w1 $end
$var wire 1 / w2 $end
$var wire 1 0 w3 $end
$var wire 1 1 w4 $end
$var wire 1 2 w5 $end
$var wire 1 3 w6 $end
$var wire 1 4 w7 $end
$upscope $end
$upscope $end
$enddefinitions $end
$comment Show the parameter values. $end
$dumpall
$end
#0
$dumpvars
04
03
02
01
00
0/
0.
1-
0,
0+
0*
0)
0(
0'
0&
0%
0$
0#
1"
1!
$end
#1
1.
0-
1#
0"
1*
#2
1/
0.
1$
0#
0*
1+
#3
10
0/
1%
0$
1*
#4
11
00
1&
0%
0*
0+
1,
#5
12
01
1'
0&
1*
#6
13
02
1(
0'
0*
1+
#7
14
03
1)
0(
1*
