Lab 3/comparator.v
    module comparator_behavorial(
    output reg less, equal, greater,
    input A3, A2, A1, A0, B3, B2, B1, B0
    );

    always @(A3 or A2 or A1 or A0 or B3 or B2 or B1 or B0)
     begin
        if(A3>B3)   begin  
            less = 0;
            equal = 0;
            greater = 1;    end
        else if(A3<B3) begin 
            less = 1;
            equal = 0;
            greater = 0;    end
        else if(A3==B3)    begin 
             if(A2>B2)   begin  
            less = 0;
            equal = 0;
            greater = 1;    end
            else if(A2<B2) begin 
            less = 1;
            equal = 0;
            greater = 0;    end
            else if(A2==B2)    begin 
                if(A1>B1)   begin  
                less = 0;
                equal = 0;
                greater = 1;    end
                else if(A1<B1) begin 
                less = 1;
                equal = 0;
                greater = 0;    end
                else if(A1==B1)    begin 
                    if(A0>B0)   begin  
                    less = 0;
                    equal = 0;
                    greater = 1;    end
                    else if(A0<B0) begin 
                    less = 1;
                    equal = 0;
                    greater = 0;    end
                    else if(A0==B0) begin 
                    less = 0;
                    equal = 1;
                    greater = 0;    end
            end
            end
        end 
    end
endmodule

Lab 3/comparator_tb.v
`include "comparator.v"
module comparartor_tb;
    reg A3,A2,A1,A0,B3,B2,B1,B0;
	wire less,equal,greater;
    comparator_behavorial Instance0(less,equal,greater,A3,A2,A1,A0,B3,B2,B1,B0);
    initial begin
        A3 = 0; A2 = 0; A1=0; A0=0; B3 = 0; B2 = 0; B1=0; B0=0;
	 #2 A3 = 1; A2 = 1; A1=1; A0=1; B3 = 1; B2 = 1; B1=1; B0=1;
	 #2 A3 = 1; A2 = 1; A1=1; A0=1; B3 = 0; B2 = 1; B1=1; B0=1;
	 #2 A3 = 0; A2 = 1; A1=1; A0=1; B3 = 1; B2 = 1; B1=1; B0=1;
	 #2 A3 = 1; A2 = 1; A1=1; A0=1; B3 = 1; B2 = 0; B1=1; B0=1;
	 #2 A3 = 1; A2 = 0; A1=1; A0=1; B3 = 1; B2 = 1; B1=1; B0=1;
	 #2 A3 = 1; A2 = 1; A1=1; A0=1; B3 = 1; B2 = 1; B1=0; B0=1;
	 #2 A3 = 1; A2 = 1; A1=0; A0=1; B3 = 1; B2 = 1; B1=1; B0=1;
	 #2 A3 = 1; A2 = 1; A1=1; A0=1; B3 = 1; B2 = 1; B1=1; B0=0;
	 #2 A3 = 1; A2 = 1; A1=1; A0=0; B3 = 1; B2 = 1; B1=1; B0=1;
	 #2 A3 = 1; A2 = 1; A1=1; A0=1; B3 = 1; B2 = 1; B1=1; B0=1;
    end
    initial begin
		$monitor ("%t | A3 = %d| B3 = %d| A2 = %d| B2 = %d| A1 = %d| B1 = %d| A0 = %d| B0 = %d| A<B = %d| A=B = %d| A>B = %d|", $time, A3,B3,A2,B2,A1,B1,A0,B0,less,equal,greater);
		$dumpfile("ab_dump.vcd");
		$dumpvars();
	end

endmodule

Lab 3/ab_dump.vcd
$date
	Tue Sep 13 16:07:52 2022
$end
$version
	Icarus Verilog
$end
$timescale
	1s
$end
$scope module comparartor_tb $end
$var wire 1 ! less $end
$var wire 1 " greater $end
$var wire 1 # equal $end
$var reg 1 $ A0 $end
$var reg 1 % A1 $end
$var reg 1 & A2 $end
$var reg 1 ' A3 $end
$var reg 1 ( B0 $end
$var reg 1 ) B1 $end
$var reg 1 * B2 $end
$var reg 1 + B3 $end
$scope module Instance0 $end
$var wire 1 $ A0 $end
$var wire 1 % A1 $end
$var wire 1 & A2 $end
$var wire 1 ' A3 $end
$var wire 1 ( B0 $end
$var wire 1 ) B1 $end
$var wire 1 * B2 $end
$var wire 1 + B3 $end
$var reg 1 # equal $end
$var reg 1 " greater $end
$var reg 1 ! less $end
$upscope $end
$upscope $end
$enddefinitions $end
$comment Show the parameter values. $end
$dumpall
$end
#0
$dumpvars
0+
0*
0)
0(
0'
0&
0%
0$
1#
0"
0!
$end
#2
1(
1)
1*
1+
1$
1%
1&
1'
#4
1"
0#
0+
#6
0"
1!
1+
0'
#8
1"
0!
0*
1'
#10
0"
1!
1*
0&
#12
1"
0!
0)
1&
#14
0"
1!
1)
0%
#16
1"
0!
0(
1%
#18
0"
1!
1(
0$
#20
1#
0!
1$
