Lab 2/Assignment.v
module Assignment ( input x1, x2, x3, output y);
    wire w1, w2, w3, w4, w5, w6;
    and and1 (w1, x1, x3);
    and and2 (w2, x1, x2);
    or or1(y, w1, w2);
endmodule

Lab 2/Assignment_tb.v
`include "Assignment.v"

module Assignment_tb;
    reg x1;
    reg x2;
    reg x3;
    wire y;

    Assignment mm0(x1, x2, x3, y);
    initial begin
        x1=0; x2=0; x3=0;
        #1 x1=0; x2=0; x3=1;
        #1 x1=0; x2=1; x3=0;
        #1 x1=0; x2=1; x3=1;
        #1 x1=1; x2=0; x3=0;
        #1 x1=1; x2=0; x3=1;
        #1 x1=1; x2=1; x3=0;
        #1 x1=1; x2=1; x3=1;
    end

    initial begin
        $monitor("T=%t | x1=%b | x2=%b |x3=%b | y=%b", $time, x1, x2, x3, y);
        $dumpfile("Assignment_tb.vcd");
        $dumpvars();
    end
endmodule

Lab 2/Assignment_tb.vcd
$date
	Tue Sep 06 08:02:43 2022
$end
$version
	Icarus Verilog
$end
$timescale
	1s
$end
$scope module Assignment_tb $end
$var wire 1 ! y $end
$var reg 1 " x1 $end
$var reg 1 # x2 $end
$var reg 1 $ x3 $end
$scope module mm0 $end
$var wire 1 % w1 $end
$var wire 1 & w2 $end
$var wire 1 " x1 $end
$var wire 1 # x2 $end
$var wire 1 $ x3 $end
$var wire 1 ! y $end
$upscope $end
$upscope $end
$enddefinitions $end
$comment Show the parameter values. $end
$dumpall
$end
#0
$dumpvars
0&
0%
0$
0#
0"
0!
$end
#1
1$
#2
0$
1#
#3
1$
#4
0$
0#
1"
#5
1!
1%
1$
#6
0%
1&
0$
1#
#7
1%
1$
