Lab 6/Mux.v
module mux(y,a,b,c,d);
input a,b,c,d;
output y;

assign y = (~b & c) | (~a & b & d) | (a & ~b);
endmodule

Lab 6/Mux_tb.v
`include "Mux.v"
module mux_tb;
    reg a,b,c,d;
    wire y;

    mux Instance0(y,a,b,c,d);
     initial begin
             a=0;b=0;c=0;d=0;
          #1 a=0;b=0;c=0;d=1;
          #1 a=0;b=0;c=1;d=0;
          #1 a=0;b=0;c=1;d=1;
          #1 a=0;b=1;c=0;d=0;
          #1 a=0;b=1;c=0;d=1;
          #1 a=0;b=1;c=1;d=0;
          #1 a=0;b=1;c=1;d=1;
          #1 a=1;b=0;c=0;d=0;
          #1 a=1;b=0;c=0;d=1;
          #1 a=1;b=0;c=1;d=0;
          #1 a=1;b=0;c=1;d=1;
          #1 a=1;b=1;c=0;d=0;
          #1 a=1;b=1;c=0;d=1;
          #1 a=1;b=1;c=1;d=0;
          #1 a=1;b=1;c=1;d=1;
        #1 ;
     end

    initial begin
        $monitor("%t | a=%b | b=%b | c=%b | d=%b | y=%b",$time,a,b,c,d,y);
        $dumpfile("mux.vcd");
        $dumpvars();	
    end
endmodule

Lab 6/mux.vcd
$date
	Fri Dec 09 02:04:40 2022
$end
$version
	Icarus Verilog
$end
$timescale
	1s
$end
$scope module mux_tb $end
$var wire 1 ! y $end
$var reg 1 " a $end
$var reg 1 # b $end
$var reg 1 $ c $end
$var reg 1 % d $end
$scope module Instance0 $end
$var wire 1 " a $end
$var wire 1 # b $end
$var wire 1 $ c $end
$var wire 1 % d $end
$var wire 1 ! y $end
$upscope $end
$upscope $end
$enddefinitions $end
$comment Show the parameter values. $end
$dumpall
$end
#0
$dumpvars
0%
0$
0#
0"
0!
$end
#1
1%
#2
1!
0%
1$
#3
1%
#4
0!
0%
0$
1#
#5
1!
1%
#6
0!
0%
1$
#7
1!
1%
#8
0%
0$
0#
1"
#9
1%
#10
0%
1$
#11
1%
#12
0!
0%
0$
1#
#13
1%
#14
0%
1$
#15
1%
