My learnings/binary_to_gray.v
module binary_to_gray (input [3:0] binary, output [3:0] gray);
    assign gray[0] = binary[0];
    assign gray[1] = binary[0] ^ binary[1];
    assign gray[2] = binary[1] ^ binary[2];
    assign gray[3] = binary[2] ^ binary[3];
endmodule

My learnings/binary_to_gray_tb.v
`include "binary_to_gray.v"

module binary_to_gray_tb;
    reg [3:0] binary;
    wire [3:0] gray;
    binary_to_gray b2g(binary, gray);
    initial begin
        binary = 4'b0000;
        #1 binary = 4'b0001;
        #1 binary = 4'b0010;
        #1 binary = 4'b0011;
        #1 binary = 4'b0100;
        #1 binary = 4'b0101;
        #1 binary = 4'b0110;
        #1 binary = 4'b0111;
        #1 binary = 4'b1000;
        #1 binary = 4'b1001;
        #1 binary = 4'b1010;
        #1 binary = 4'b1011;
        #1 binary = 4'b1100;
        #1 binary = 4'b1101;
        #1 binary = 4'b1110;
        #1 binary = 4'b1111;
        #1 ;
    end
    initial begin
        $monitor("%t | %b | %b",$time,binary,gray);
        $dumpfile("binary_to_gray.vcd");
        $dumpvars();	
    end
endmodule

// Path: My learnings\binary_to_gray.v

My learnings/binary_to_gray.vcd
$date
	Wed Jan 18 19:20:56 2023
$end
$version
	Icarus Verilog
$end
$timescale
	1s
$end
$scope module binary_to_gray_tb $end
$var wire 4 ! gray [3:0] $end
$var reg 4 " binary [3:0] $end
$scope module b2g $end
$var wire 4 # binary [3:0] $end
$var wire 4 $ gray [3:0] $end
$upscope $end
$upscope $end
$enddefinitions $end
$comment Show the parameter values. $end
$dumpall
$end
#0
$dumpvars
b0 $
b0 #
b0 "
b0 !
$end
#1
b11 !
b11 $
b1 "
b1 #
#2
b110 !
b110 $
b10 "
b10 #
#3
b101 !
b101 $
b11 "
b11 #
#4
b1100 !
b1100 $
b100 "
b100 #
#5
b1111 !
b1111 $
b101 "
b101 #
#6
b1010 !
b1010 $
b110 "
b110 #
#7
b1001 !
b1001 $
b111 "
b111 #
#8
b1000 !
b1000 $
b1000 "
b1000 #
#9
b1011 !
b1011 $
b1001 "
b1001 #
#10
b1110 !
b1110 $
b1010 "
b1010 #
#11
b1101 !
b1101 $
b1011 "
b1011 #
#12
b100 !
b100 $
b1100 "
b1100 #
#13
b111 !
b111 $
b1101 "
b1101 #
#14
b10 !
b10 $
b1110 "
b1110 #
#15
b1 !
b1 $
b1111 "
b1111 #
